CHANGELOG.md
LICENSE
README.md
mics6814/__init__.py
pimoroni_mics6814-1.0.0.dist-info/METADATA
pimoroni_mics6814-1.0.0.dist-info/WHEEL
pimoroni_mics6814-1.0.0.dist-info/licenses/LICENSE
pimoroni_mics6814-1.0.0.dist-info/RECORD
